{
  "url": "https://api.github.com/repos/sCrypt-Inc/compiler_dist/releases/65546038",
  "assets_url": "https://api.github.com/repos/sCrypt-Inc/compiler_dist/releases/65546038/assets",
  "upload_url": "https://uploads.github.com/repos/sCrypt-Inc/compiler_dist/releases/65546038/assets{?name,label}",
  "html_url": "https://github.com/sCrypt-Inc/compiler_dist/releases/tag/v1.13.2",
  "id": 65546038,
  "author": {
    "login": "scrypt-sv",
    "id": 52027588,
    "node_id": "MDQ6VXNlcjUyMDI3NTg4",
    "avatar_url": "https://avatars.githubusercontent.com/u/52027588?v=4",
    "gravatar_id": "",
    "url": "https://api.github.com/users/scrypt-sv",
    "html_url": "https://github.com/scrypt-sv",
    "followers_url": "https://api.github.com/users/scrypt-sv/followers",
    "following_url": "https://api.github.com/users/scrypt-sv/following{/other_user}",
    "gists_url": "https://api.github.com/users/scrypt-sv/gists{/gist_id}",
    "starred_url": "https://api.github.com/users/scrypt-sv/starred{/owner}{/repo}",
    "subscriptions_url": "https://api.github.com/users/scrypt-sv/subscriptions",
    "organizations_url": "https://api.github.com/users/scrypt-sv/orgs",
    "repos_url": "https://api.github.com/users/scrypt-sv/repos",
    "events_url": "https://api.github.com/users/scrypt-sv/events{/privacy}",
    "received_events_url": "https://api.github.com/users/scrypt-sv/received_events",
    "type": "User",
    "site_admin": false
  },
  "node_id": "RE_kwDOEskUbM4D6Cc2",
  "tag_name": "v1.13.2",
  "target_commitish": "master",
  "name": "refs/tags/v1.13.2",
  "draft": false,
  "prerelease": false,
  "created_at": "2022-04-27T16:18:42Z",
  "published_at": "2022-04-28T07:20:05Z",
  "assets": [
    {
      "url": "https://api.github.com/repos/sCrypt-Inc/compiler_dist/releases/assets/63879863",
      "id": 63879863,
      "node_id": "RA_kwDOEskUbM4Dzrq3",
      "name": "scryptc-1.13.2-Linux",
      "label": "",
      "uploader": {
        "login": "scrypt-sv",
        "id": 52027588,
        "node_id": "MDQ6VXNlcjUyMDI3NTg4",
        "avatar_url": "https://avatars.githubusercontent.com/u/52027588?v=4",
        "gravatar_id": "",
        "url": "https://api.github.com/users/scrypt-sv",
        "html_url": "https://github.com/scrypt-sv",
        "followers_url": "https://api.github.com/users/scrypt-sv/followers",
        "following_url": "https://api.github.com/users/scrypt-sv/following{/other_user}",
        "gists_url": "https://api.github.com/users/scrypt-sv/gists{/gist_id}",
        "starred_url": "https://api.github.com/users/scrypt-sv/starred{/owner}{/repo}",
        "subscriptions_url": "https://api.github.com/users/scrypt-sv/subscriptions",
        "organizations_url": "https://api.github.com/users/scrypt-sv/orgs",
        "repos_url": "https://api.github.com/users/scrypt-sv/repos",
        "events_url": "https://api.github.com/users/scrypt-sv/events{/privacy}",
        "received_events_url": "https://api.github.com/users/scrypt-sv/received_events",
        "type": "User",
        "site_admin": false
      },
      "content_type": "binary/octet-stream",
      "state": "uploaded",
      "size": 12319056,
      "download_count": 1,
      "created_at": "2022-04-28T07:20:06Z",
      "updated_at": "2022-04-28T07:20:06Z",
      "browser_download_url": "https://github.com/sCrypt-Inc/compiler_dist/releases/download/v1.13.2/scryptc-1.13.2-Linux"
    },
    {
      "url": "https://api.github.com/repos/sCrypt-Inc/compiler_dist/releases/assets/63880054",
      "id": 63880054,
      "node_id": "RA_kwDOEskUbM4Dzrt2",
      "name": "scryptc-1.13.2-macOS",
      "label": "",
      "uploader": {
        "login": "scrypt-sv",
        "id": 52027588,
        "node_id": "MDQ6VXNlcjUyMDI3NTg4",
        "avatar_url": "https://avatars.githubusercontent.com/u/52027588?v=4",
        "gravatar_id": "",
        "url": "https://api.github.com/users/scrypt-sv",
        "html_url": "https://github.com/scrypt-sv",
        "followers_url": "https://api.github.com/users/scrypt-sv/followers",
        "following_url": "https://api.github.com/users/scrypt-sv/following{/other_user}",
        "gists_url": "https://api.github.com/users/scrypt-sv/gists{/gist_id}",
        "starred_url": "https://api.github.com/users/scrypt-sv/starred{/owner}{/repo}",
        "subscriptions_url": "https://api.github.com/users/scrypt-sv/subscriptions",
        "organizations_url": "https://api.github.com/users/scrypt-sv/orgs",
        "repos_url": "https://api.github.com/users/scrypt-sv/repos",
        "events_url": "https://api.github.com/users/scrypt-sv/events{/privacy}",
        "received_events_url": "https://api.github.com/users/scrypt-sv/received_events",
        "type": "User",
        "site_admin": false
      },
      "content_type": "binary/octet-stream",
      "state": "uploaded",
      "size": 6732248,
      "download_count": 0,
      "created_at": "2022-04-28T07:23:17Z",
      "updated_at": "2022-04-28T07:23:18Z",
      "browser_download_url": "https://github.com/sCrypt-Inc/compiler_dist/releases/download/v1.13.2/scryptc-1.13.2-macOS"
    },
    {
      "url": "https://api.github.com/repos/sCrypt-Inc/compiler_dist/releases/assets/63880220",
      "id": 63880220,
      "node_id": "RA_kwDOEskUbM4Dzrwc",
      "name": "scryptc-1.13.2-Windows.exe",
      "label": "",
      "uploader": {
        "login": "scrypt-sv",
        "id": 52027588,
        "node_id": "MDQ6VXNlcjUyMDI3NTg4",
        "avatar_url": "https://avatars.githubusercontent.com/u/52027588?v=4",
        "gravatar_id": "",
        "url": "https://api.github.com/users/scrypt-sv",
        "html_url": "https://github.com/scrypt-sv",
        "followers_url": "https://api.github.com/users/scrypt-sv/followers",
        "following_url": "https://api.github.com/users/scrypt-sv/following{/other_user}",
        "gists_url": "https://api.github.com/users/scrypt-sv/gists{/gist_id}",
        "starred_url": "https://api.github.com/users/scrypt-sv/starred{/owner}{/repo}",
        "subscriptions_url": "https://api.github.com/users/scrypt-sv/subscriptions",
        "organizations_url": "https://api.github.com/users/scrypt-sv/orgs",
        "repos_url": "https://api.github.com/users/scrypt-sv/repos",
        "events_url": "https://api.github.com/users/scrypt-sv/events{/privacy}",
        "received_events_url": "https://api.github.com/users/scrypt-sv/received_events",
        "type": "User",
        "site_admin": false
      },
      "content_type": "binary/octet-stream",
      "state": "uploaded",
      "size": 13144576,
      "download_count": 0,
      "created_at": "2022-04-28T07:25:45Z",
      "updated_at": "2022-04-28T07:25:46Z",
      "browser_download_url": "https://github.com/sCrypt-Inc/compiler_dist/releases/download/v1.13.2/scryptc-1.13.2-Windows.exe"
    }
  ],
  "tarball_url": "https://api.github.com/repos/sCrypt-Inc/compiler_dist/tarball/v1.13.2",
  "zipball_url": "https://api.github.com/repos/sCrypt-Inc/compiler_dist/zipball/v1.13.2",
  "body": "Compiler binaries"
}
